bayeso_benchmarks/__init__.py
bayeso_benchmarks/benchmark_base.py
bayeso_benchmarks/four_dim_colville.py
bayeso_benchmarks/inf_dim_ackley.py
bayeso_benchmarks/inf_dim_cosines.py
bayeso_benchmarks/inf_dim_griewank.py
bayeso_benchmarks/inf_dim_levy.py
bayeso_benchmarks/inf_dim_rastrigin.py
bayeso_benchmarks/inf_dim_rosenbrock.py
bayeso_benchmarks/inf_dim_sphere.py
bayeso_benchmarks/inf_dim_zakharov.py
bayeso_benchmarks/one_dim_constant.py
bayeso_benchmarks/one_dim_gramacyandlee2012.py
bayeso_benchmarks/one_dim_linear.py
bayeso_benchmarks/one_dim_step.py
bayeso_benchmarks/six_dim_hartmann6d.py
bayeso_benchmarks/three_dim_hartmann3d.py
bayeso_benchmarks/two_dim_beale.py
bayeso_benchmarks/two_dim_bohachevsky.py
bayeso_benchmarks/two_dim_branin.py
bayeso_benchmarks/two_dim_bukin6.py
bayeso_benchmarks/two_dim_dejong5.py
bayeso_benchmarks/two_dim_dropwave.py
bayeso_benchmarks/two_dim_easom.py
bayeso_benchmarks/two_dim_eggholder.py
bayeso_benchmarks/two_dim_goldsteinprice.py
bayeso_benchmarks/two_dim_holdertable.py
bayeso_benchmarks/two_dim_kim1.py
bayeso_benchmarks/two_dim_kim2.py
bayeso_benchmarks/two_dim_kim3.py
bayeso_benchmarks/two_dim_michalewicz.py
bayeso_benchmarks/two_dim_shubert.py
bayeso_benchmarks/two_dim_sixhumpcamel.py
bayeso_benchmarks/two_dim_threehumpcamel.py
bayeso_benchmarks/utils.py
bayeso_benchmarks-0.2.0.dist-info/LICENSE
bayeso_benchmarks-0.2.0.dist-info/METADATA
bayeso_benchmarks-0.2.0.dist-info/WHEEL
bayeso_benchmarks-0.2.0.dist-info/top_level.txt
bayeso_benchmarks-0.2.0.dist-info/RECORD
