Metadata-Version: 2.1
Name: bayeso-benchmarks
Version: 0.2.0
Summary: Benchmark functions for Bayesian optimization
Author-email: Jungtaek Kim <jungtaek.kim.mail@gmail.com>
License: MIT
Project-URL: Homepage, https://bayeso.org
Project-URL: Source, https://github.com/jungtaekkim/bayeso-benchmarks
Project-URL: Issues, https://github.com/jungtaekkim/bayeso-benchmarks/issues
Classifier: Programming Language :: Python :: 3
Classifier: Intended Audience :: Science/Research
Classifier: License :: OSI Approved :: MIT License
Classifier: Operating System :: OS Independent
Classifier: Topic :: Scientific/Engineering
Classifier: Topic :: Scientific/Engineering :: Artificial Intelligence
Requires-Python: >=3.7
License-File: LICENSE
Requires-Dist: numpy
Provides-Extra: dev
Requires-Dist: pytest ; extra == 'dev'
Requires-Dist: wheel ; extra == 'dev'
Requires-Dist: build ; extra == 'dev'
Requires-Dist: twine ; extra == 'dev'
Requires-Dist: scipy ; extra == 'dev'
Requires-Dist: matplotlib ; extra == 'dev'
